{
  "id": "the-emperors-edge",
  "license": "CC0-1.0",
  "name": "The Emperor's Edge",
  "sources": [
    {
      "imported_at": "2026-07-11",
      "ref": "B07RZVXNKP",
      "type": "openaudible-import"
    }
  ],
  "works": [
    {
      "position": "5.5",
      "work": "beneath-the-surface"
    },
    {
      "position": "2",
      "work": "dark-currents"
    },
    {
      "position": "6",
      "work": "forged-in-blood-part-1"
    },
    {
      "position": "7",
      "work": "forged-in-blood-part-2"
    },
    {
      "position": "3",
      "work": "deadly-games"
    },
    {
      "position": "4",
      "work": "conspiracy"
    },
    {
      "position": "5",
      "work": "blood-and-betrayal"
    }
  ]
}
